napari_folder_browser/__init__.py
napari_folder_browser/_dock_widget.py
napari_folder_browser/_tests/__init__.py
napari_folder_browser/_tests/test_dock_widget.py
napari_folder_browser-0.1.4.dist-info/LICENSE
napari_folder_browser-0.1.4.dist-info/METADATA
napari_folder_browser-0.1.4.dist-info/WHEEL
napari_folder_browser-0.1.4.dist-info/entry_points.txt
napari_folder_browser-0.1.4.dist-info/top_level.txt
napari_folder_browser-0.1.4.dist-info/RECORD
