Metadata-Version: 2.1
Name: napari-folder-browser
Version: 0.1.4
Summary: Browse folders of images and open them using double-click
Home-page: https://github.com/haesleinhuepf/napari-folder-browser
Author: Robert Haase
Author-email: robert.haase@tu-dresden.de
License: BSD-3-Clause
Project-URL: Bug Tracker, https://github.com/haesleinhuepf/napari-folder-browser/issues
Project-URL: Documentation, https://github.com/haesleinhuepf/napari-folder-browser#README.md
Project-URL: Source Code, https://github.com/haesleinhuepf/napari-folder-browser
Project-URL: User Support, https://github.com/haesleinhuepf/napari-folder-browser/issues
Classifier: Development Status :: 3 - Alpha
Classifier: Intended Audience :: Science/Research
Classifier: Framework :: napari
Classifier: Topic :: Scientific/Engineering :: Image Processing
Classifier: Programming Language :: Python
Classifier: Programming Language :: Python :: 3
Classifier: Programming Language :: Python :: 3.7
Classifier: Programming Language :: Python :: 3.8
Classifier: Programming Language :: Python :: 3.9
Classifier: Operating System :: OS Independent
Classifier: License :: OSI Approved :: BSD License
Requires-Python: >=3.7
License-File: LICENSE
Requires-Dist: napari-plugin-engine >=0.1.4
Requires-Dist: napari-tools-menu
